{
  "site": {
    "url": "https://blakefolgado.com/",
    "title": "Blake Folgado",
    "description": "Designer who likes to make products.",
    "timezone": "Europe/London",
    "locationLabel": "London",
    "weather": {
      "latitude": 51.5074,
      "longitude": -0.1278
    },
    "images": {
      "og": "https://blakefolgado.com/og.png",
      "profile": "https://pbs.twimg.com/profile_images/1965432976679796737/a4clo-mr.jpg"
    }
  },
  "person": {
    "name": "Blake Folgado",
    "tagline": "Designer who likes to make products.",
    "email": "blake@blakefolgado.com",
    "socials": [
      {
        "label": "X",
        "url": "https://x.com/blakefolgado"
      },
      {
        "label": "Email",
        "url": "mailto:blake@blakefolgado.com"
      }
    ]
  },
  "projects": [
    {
      "name": "Outside",
      "subtitle": "Make things happen in real life!",
      "url": "https://outside.so",
      "image": "/assets/outside.png"
    },
    {
      "name": "Toolrouter",
      "subtitle": "The easiest way to route AI tools",
      "url": "https://toolrouter.com",
      "image": "/assets/toolrouter.ico"
    },
    {
      "name": "Book Sparky",
      "subtitle": "AI-powered booking assistant",
      "url": "https://book-sparky.com",
      "image": "/assets/booksparky.png"
    },
    {
      "name": "Sentrydock",
      "subtitle": "AI analyst for traders",
      "url": "https://sentrydock.com",
      "image": "/assets/sentrydock.png"
    },
    {
      "name": "Famchat",
      "subtitle": "Safe AI app for families",
      "url": "https://famchatapp.com",
      "image": "/assets/famchat.ico"
    },
    {
      "name": "Magic Screenshots",
      "subtitle": "Instantly beautiful product shots",
      "url": "https://magicscreenshots.com",
      "image": "/assets/magicscreenshots.png"
    }
  ],
  "facts": [
    {
      "label": "Previous Product Director at Cuvva",
      "url": "https://www.cuvva.com",
      "icon": "/assets/cuvva.png"
    },
    {
      "label": "Cohort 3 at Entrepreneur First",
      "url": "https://www.joinef.com",
      "icon": "/assets/joinef.png"
    },
    {
      "label": "Used to be a toy designer"
    },
    {
      "label": "Angel investor once"
    },
    {
      "label": "Speculator"
    },
    {
      "label": "Love Sci-Fi"
    },
    {
      "label": "Audiobooks over reading"
    }
  ],
  "talks": [
    {
      "label": "Scaling design at Cuvva",
      "url": "https://www.youtube.com/watch?v=6wkWyox00ec"
    },
    {
      "label": "Talk at Figma London",
      "url": "https://www.youtube.com/watch?v=zj4K_iMKTIY&t=2405s"
    }
  ]
}
